llama_recommendation/__init__.py
llama_recommendation/causal_counterfactual.py
llama_recommendation/causal_uplift.py
llama_recommendation/config.py
llama_recommendation/core.py
llama_recommendation/core_models.py
llama_recommendation/embeddings.py
llama_recommendation/ethics_diversity.py
llama_recommendation/ethics_fairness.py
llama_recommendation/ethics_guidelines.py
llama_recommendation/federated_aggregation.py
llama_recommendation/federated_client.py
llama_recommendation/federated_server.py
llama_recommendation/graph_gcn.py
llama_recommendation/graph_relations.py
llama_recommendation/image_encoder.py
llama_recommendation/mobile_coreml.py
llama_recommendation/multimodal_encoder.py
llama_recommendation/privacy.py
llama_recommendation/recommendation_candidate.py
llama_recommendation/recommendation_explanation.py
llama_recommendation/recommendation_filtering.py
llama_recommendation/recommendation_ranking.py
llama_recommendation/recommender.py
llama_recommendation/security_encryption.py
llama_recommendation/security_keys.py
llama_recommendation/text_encoder.py
llama_recommendation/utils_config.py
llama_recommendation/utils_data.py
llama_recommendation/utils_logging.py
llama_recommendation-0.1.0.dist-info/METADATA
llama_recommendation-0.1.0.dist-info/WHEEL
llama_recommendation-0.1.0.dist-info/licenses/LICENSE
llama_recommendation-0.1.0.dist-info/RECORD
