Metadata-Version: 2.4
Name: llama-recommendation
Version: 0.1.0
Summary: Privacy-preserving multi-modal recommendation system
Project-URL: Homepage, https://github.com/yourusername/llamasearchai-git2-copy
Project-URL: Bug Tracker, https://github.com/yourusername/llamasearchai-git2-copy/issues
Project-URL: Documentation, https://llama-recommendation.readthedocs.io
Author-email: Your Name / Llama Team <your.email@example.com>
License: MIT
License-File: LICENSE
Classifier: Development Status :: 4 - Beta
Classifier: Intended Audience :: Developers
Classifier: Intended Audience :: Science/Research
Classifier: License :: OSI Approved :: MIT License
Classifier: Programming Language :: Python :: 3
Classifier: Programming Language :: Python :: 3.9
Classifier: Programming Language :: Python :: 3.10
Classifier: Programming Language :: Python :: 3.11
Classifier: Topic :: Scientific/Engineering :: Artificial Intelligence
Classifier: Topic :: Software Development :: Libraries :: Python Modules
Requires-Python: >=3.9
Requires-Dist: cryptography>=38.0.0
Requires-Dist: fastapi>=0.95.0
Requires-Dist: joblib>=1.1.0
Requires-Dist: matplotlib>=3.4.0
Requires-Dist: mlx>=0.3.0
Requires-Dist: networkx>=2.6.0
Requires-Dist: numpy>=1.20.0
Requires-Dist: pandas>=1.3.0
Requires-Dist: pillow>=9.0.0
Requires-Dist: pydantic>=2.0.0
Requires-Dist: python-dotenv>=0.19.0
Requires-Dist: requests>=2.28.0
Requires-Dist: scikit-learn>=1.0.0
Requires-Dist: scipy>=1.7.0
Requires-Dist: tqdm>=4.62.0
Requires-Dist: typing-extensions>=4.3.0
Provides-Extra: coreml
Requires-Dist: coremltools>=6.0.0; extra == 'coreml'
Provides-Extra: dev
Requires-Dist: bandit; extra == 'dev'
Requires-Dist: black>=23.0.0; extra == 'dev'
Requires-Dist: build; extra == 'dev'
Requires-Dist: isort>=5.10.0; extra == 'dev'
Requires-Dist: mypy>=1.0.0; extra == 'dev'
Requires-Dist: pre-commit>=3.0.0; extra == 'dev'
Requires-Dist: pytest-cov>=4.0.0; extra == 'dev'
Requires-Dist: pytest-mock; extra == 'dev'
Requires-Dist: pytest>=7.0.0; extra == 'dev'
Requires-Dist: ruff>=0.0.230; extra == 'dev'
Requires-Dist: safety; extra == 'dev'
Requires-Dist: twine; extra == 'dev'
Requires-Dist: types-requests; extra == 'dev'
Provides-Extra: docs
Requires-Dist: sphinx-autodoc-typehints>=1.18.0; extra == 'docs'
Requires-Dist: sphinx-rtd-theme>=1.0.0; extra == 'docs'
Requires-Dist: sphinx>=5.0.0; extra == 'docs'
Provides-Extra: pytorch
Requires-Dist: torch>=2.0.0; extra == 'pytorch'
Requires-Dist: torchvision>=0.15.0; extra == 'pytorch'
Provides-Extra: tf
Requires-Dist: tensorflow>=2.10.0; extra == 'tf'
